python_viem/__init__.py
python_viem/viem-chains.json
python_viem/viem.py
python_viem-0.1.2.dist-info/METADATA
python_viem-0.1.2.dist-info/WHEEL
python_viem-0.1.2.dist-info/top_level.txt
python_viem-0.1.2.dist-info/RECORD
