Metadata-Version: 2.4
Name: python-viem
Version: 0.1.2
Summary: Python library for viem chain metadata, enabling compatibility with Javascript tooling.
License: MIT
Requires-Python: <4.0,>=3.7
Requires-Dist: requests>=2.31.0
Provides-Extra: dev
Requires-Dist: build>=1.1.1; extra == "dev"
Requires-Dist: twine>=4.0.2; extra == "dev"
